MANIFEST.in
README.txt
setup.cfg
setup.py
atreal/__init__.py
atreal/__init__.pyc
atreal.portlet.backwardlinks.egg-info/PKG-INFO
atreal.portlet.backwardlinks.egg-info/SOURCES.txt
atreal.portlet.backwardlinks.egg-info/dependency_links.txt
atreal.portlet.backwardlinks.egg-info/entry_points.txt
atreal.portlet.backwardlinks.egg-info/namespace_packages.txt
atreal.portlet.backwardlinks.egg-info/not-zip-safe
atreal.portlet.backwardlinks.egg-info/requires.txt
atreal.portlet.backwardlinks.egg-info/top_level.txt
atreal/portlet/__init__.py
atreal/portlet/__init__.pyc
atreal/portlet/backwardlinks/__init__.py
atreal/portlet/backwardlinks/backwardlinksportlet.pt
atreal/portlet/backwardlinks/backwardlinksportlet.py
atreal/portlet/backwardlinks/configure.zcml
atreal/portlet/backwardlinks/locales/atreal.portlet.backwardlinks.pot
atreal/portlet/backwardlinks/locales/fr/LC_MESSAGES/atreal.portlet.backwardlinks.po
atreal/portlet/backwardlinks/profiles/default/metadata.xml
atreal/portlet/backwardlinks/profiles/default/portlets.xml
atreal/portlet/backwardlinks/tests/__init__.py
atreal/portlet/backwardlinks/tests/base.py
atreal/portlet/backwardlinks/tests/test_portlet.py