Metadata-Version: 1.0
Name: atreal.portlet.backwardlinks
Version: 1.0.0
Summary: A portlet to display backward links
Home-page: http://www.atreal.net
Author: atReal
Author-email: contact@atreal.net
License: GPL
Keywords: plone atreal portlet backward links
Platform: UNKNOWN
Classifier: Framework :: Plone
Classifier: Programming Language :: Python
Classifier: Topic :: Software Development :: Libraries :: Python Modules
